dockipy/__about__.py
dockipy/__init__.py
dockipy/dockibook.py
dockipy/dockipy.py
dockipy/dockishell.py
dockipy/envibook.py
dockipy/envipy.py
dockipy/utils.py
dockipy-0.0.92.dist-info/METADATA
dockipy-0.0.92.dist-info/WHEEL
dockipy-0.0.92.dist-info/entry_points.txt
dockipy-0.0.92.dist-info/licenses/LICENSE
dockipy-0.0.92.dist-info/RECORD
