Metadata-Version: 2.4
Name: dockipy
Version: 0.0.92
Project-URL: Documentation, https://github.com/Arty-Facts/dockipy#readme
Project-URL: Issues, https://github.com/Arty-Facts/dockipy/issues
Project-URL: Source, https://github.com/Arty-Facts/dockipy
Author-email: Arturas Aleksandraus <arturas@aleksandraus.se>
License-Expression: Apache-2.0
License-File: LICENSE
Classifier: Development Status :: 3 - Alpha
Classifier: Programming Language :: Python
Classifier: Programming Language :: Python :: 3.8
Classifier: Programming Language :: Python :: 3.9
Classifier: Programming Language :: Python :: 3.10
Classifier: Programming Language :: Python :: 3.11
Classifier: Programming Language :: Python :: 3.12
Classifier: Programming Language :: Python :: Implementation :: CPython
Classifier: Programming Language :: Python :: Implementation :: PyPy
Requires-Python: >=3.8
Requires-Dist: docker
Requires-Dist: libtmux
Requires-Dist: pyyaml
Requires-Dist: typing-extensions
